{
  "code": 0,
  "msg": "",
  "count": 1000,
  "data": [
    {
      "id": 10000,
      "username": "牙刷",
      "sex": "20",
      "yunfei":"0.00",
      "city": "20",
      "sign": "香玲生活用品店",
      "experience": "陕西省xx市xx区xx街道xx小区xxx",
      "logins": "王建坤",
      "wealth": "无",
      "wuliu":"正在运输",
      "fukuan":"微信"
    },
	{
	  "id": 10000,
	  "username": "牙刷",
	  "sex": "20",
	  "yunfei":"0.00",
	  "city": "20",
	  "sign": "香玲生活用品店",
	  "experience": "陕西省xx市xx区xx街道xx小区xxx",
	  "logins": "王建坤",
	  "wealth": "无",
	  "wuliu":"正在运输",
	  "fukuan":"微信"
	},
	{
	  "id": 10000,
	  "username": "牙刷",
	  "sex": "20",
	  "yunfei":"0.00",
	  "city": "20",
	  "sign": "香玲生活用品店",
	  "experience": "陕西省xx市xx区xx街道xx小区xxx",
	  "logins": "王建坤",
	  "wealth": "无",
	  "wuliu":"正在运输",
	  "fukuan":"微信"
	},
	{
	  "id": 10000,
	  "username": "牙刷",
	  "sex": "20",
	  "yunfei":"0.00",
	  "city": "20",
	  "sign": "香玲生活用品店",
	  "experience": "陕西省xx市xx区xx街道xx小区xxx",
	  "logins": "王建坤",
	  "wealth": "无",
	  "wuliu":"正在运输",
	  "fukuan":"微信"
	},
	{
	  "id": 10000,
	  "username": "牙刷",
	  "sex": "20",
	  "yunfei":"0.00",
	  "city": "20",
	  "sign": "香玲生活用品店",
	  "experience": "陕西省xx市xx区xx街道xx小区xxx",
	  "logins": "王建坤",
	  "wealth": "无",
	  "wuliu":"正在运输",
	  "fukuan":"微信"
	},
	{
	  "id": 10000,
	  "username": "牙刷",
	  "sex": "20",
	  "yunfei":"0.00",
	  "city": "20",
	  "sign": "香玲生活用品店",
	  "experience": "陕西省xx市xx区xx街道xx小区xxx",
	  "logins": "王建坤",
	  "wealth": "无",
	  "wuliu":"正在运输",
	  "fukuan":"微信"
	},
	{
	  "id": 10000,
	  "username": "牙刷",
	  "sex": "20",
	  "yunfei":"0.00",
	  "city": "20",
	  "sign": "香玲生活用品店",
	  "experience": "陕西省xx市xx区xx街道xx小区xxx",
	  "logins": "王建坤",
	  "wealth": "无",
	  "wuliu":"正在运输",
	  "fukuan":"微信"
	},
	{
	  "id": 10000,
	  "username": "牙刷",
	  "sex": "20",
	  "yunfei":"0.00",
	  "city": "20",
	  "sign": "香玲生活用品店",
	  "experience": "陕西省xx市xx区xx街道xx小区xxx",
	  "logins": "王建坤",
	  "wealth": "无",
	  "wuliu":"正在运输",
	  "fukuan":"微信"
	},
	{
	  "id": 10000,
	  "username": "牙刷",
	  "sex": "20",
	  "yunfei":"0.00",
	  "city": "20",
	  "sign": "香玲生活用品店",
	  "experience": "陕西省xx市xx区xx街道xx小区xxx",
	  "logins": "王建坤",
	  "wealth": "无",
	  "wuliu":"正在运输",
	  "fukuan":"微信"
	},
	{
	  "id": 10000,
	  "username": "牙刷",
	  "sex": "20",
	  "yunfei":"0.00",
	  "city": "20",
	  "sign": "香玲生活用品店",
	  "experience": "陕西省xx市xx区xx街道xx小区xxx",
	  "logins": "王建坤",
	  "wealth": "无",
	  "wuliu":"正在运输",
	  "fukuan":"微信"
	},   {
     "id": 10000,
     "username": "牙刷",
     "sex": "20",
     "yunfei":"0.00",
     "city": "20",
     "sign": "香玲生活用品店",
     "experience": "陕西省xx市xx区xx街道xx小区xxx",
     "logins": "王建坤",
     "wealth": "无",
     "wuliu":"正在运输",
     "fukuan":"微信"
   },
   {
     "id": 10000,
     "username": "牙刷",
     "sex": "20",
     "yunfei":"0.00",
     "city": "20",
     "sign": "香玲生活用品店",
     "experience": "陕西省xx市xx区xx街道xx小区xxx",
     "logins": "王建坤",
     "wealth": "无",
     "wuliu":"正在运输",
     "fukuan":"微信"
   },
   {
     "id": 10000,
     "username": "牙刷",
     "sex": "20",
     "yunfei":"0.00",
     "city": "20",
     "sign": "香玲生活用品店",
     "experience": "陕西省xx市xx区xx街道xx小区xxx",
     "logins": "王建坤",
     "wealth": "无",
     "wuliu":"正在运输",
     "fukuan":"微信"
   },
   
   {
     "id": 10000,
     "username": "牙刷",
     "sex": "20",
     "yunfei":"0.00",
     "city": "20",
     "sign": "香玲生活用品店",
     "experience": "陕西省xx市xx区xx街道xx小区xxx",
     "logins": "王建坤",
     "wealth": "无",
     "wuliu":"正在运输",
     "fukuan":"微信"
   },
   {
     "id": 10000,
     "username": "牙刷",
     "sex": "20",
     "yunfei":"0.00",
     "city": "20",
     "sign": "香玲生活用品店",
     "experience": "陕西省xx市xx区xx街道xx小区xxx",
     "logins": "王建坤",
     "wealth": "无",
     "wuliu":"正在运输",
     "fukuan":"微信"
   }
  ]
}